{"status":true,"err_id":"","err_code":"","err_msg":"","data":{"rank_data":[{"race":"2018-03-26","rank":"1","uid":"0","account":"Valerchik","game":"2","currency":"1","amount":"13639","avatar":null,"avatar_base64":null,"amount_format":"13,639"},{"race":"2018-03-26","rank":"2","uid":"0","account":"spinzter","game":"2","currency":"1","amount":"11200","avatar":null,"avatar_base64":null,"amount_format":"11,200"},{"race":"2018-03-26","rank":"3","uid":"0","account":"Juhazzz","game":"2","currency":"1","amount":"8825","avatar":null,"avatar_base64":null,"amount_format":"8,825"},{"race":"2018-03-26","rank":"4","uid":"0","account":"PeakingDuck","game":"2","currency":"1","amount":"8657","avatar":null,"avatar_base64":null,"amount_format":"8,657"},{"race":"2018-03-26","rank":"5","uid":"0","account":"danieldukan","game":"2","currency":"1","amount":"8090","avatar":null,"avatar_base64":null,"amount_format":"8,090"},{"race":"2018-03-26","rank":"6","uid":"0","account":"PenDoraa","game":"2","currency":"1","amount":"8073","avatar":null,"avatar_base64":null,"amount_format":"8,073"},{"race":"2018-03-26","rank":"7","uid":"0","account":"kekzemon","game":"2","currency":"1","amount":"7948","avatar":null,"avatar_base64":null,"amount_format":"7,948"},{"race":"2018-03-26","rank":"8","uid":"0","account":"xViscooo","game":"2","currency":"1","amount":"7010","avatar":null,"avatar_base64":null,"amount_format":"7,010"},{"race":"2018-03-26","rank":"9","uid":"0","account":"ywsandcj","game":"2","currency":"1","amount":"6945","avatar":null,"avatar_base64":null,"amount_format":"6,945"},{"race":"2018-03-26","rank":"10","uid":"0","account":"gigawayss","game":"2","currency":"1","amount":"6932","avatar":null,"avatar_base64":null,"amount_format":"6,932"},{"race":"2018-03-26","rank":"11","uid":"0","account":"Hizbasba","game":"2","currency":"1","amount":"6782","avatar":null,"avatar_base64":null,"amount_format":"6,782"},{"race":"2018-03-26","rank":"12","uid":"0","account":"Runner84","game":"2","currency":"1","amount":"6762","avatar":null,"avatar_base64":null,"amount_format":"6,762"},{"race":"2018-03-26","rank":"13","uid":"0","account":"toiletsnake","game":"2","currency":"1","amount":"6558","avatar":null,"avatar_base64":null,"amount_format":"6,558"},{"race":"2018-03-26","rank":"14","uid":"0","account":"RedhillRed","game":"2","currency":"1","amount":"6430","avatar":null,"avatar_base64":null,"amount_format":"6,430"},{"race":"2018-03-26","rank":"15","uid":"0","account":"DuckzDuck","game":"2","currency":"1","amount":"6230","avatar":null,"avatar_base64":null,"amount_format":"6,230"},{"race":"2018-03-26","rank":"16","uid":"0","account":"bluegray","game":"2","currency":"1","amount":"6226","avatar":null,"avatar_base64":null,"amount_format":"6,226"},{"race":"2018-03-26","rank":"17","uid":"0","account":"BarrettLightFifty","game":"2","currency":"1","amount":"6219","avatar":null,"avatar_base64":null,"amount_format":"6,219"},{"race":"2018-03-26","rank":"18","uid":"0","account":"Mohunhuhuo","game":"2","currency":"1","amount":"6149","avatar":null,"avatar_base64":null,"amount_format":"6,149"},{"race":"2018-03-26","rank":"19","uid":"0","account":"Nurgusgu","game":"2","currency":"1","amount":"6143","avatar":null,"avatar_base64":null,"amount_format":"6,143"},{"race":"2018-03-26","rank":"20","uid":"0","account":"zeldzioszka","game":"2","currency":"1","amount":"6142","avatar":null,"avatar_base64":null,"amount_format":"6,142"},{"race":"2018-03-26","rank":"21","uid":"0","account":"Japichin","game":"2","currency":"1","amount":"6140","avatar":null,"avatar_base64":null,"amount_format":"6,140"},{"race":"2018-03-26","rank":"22","uid":"0","account":"spartanobr","game":"2","currency":"1","amount":"6099","avatar":null,"avatar_base64":null,"amount_format":"6,099"},{"race":"2018-03-26","rank":"23","uid":"0","account":"MagicalPowers","game":"2","currency":"1","amount":"5984","avatar":null,"avatar_base64":null,"amount_format":"5,984"},{"race":"2018-03-26","rank":"24","uid":"0","account":"DukeLBHoon","game":"2","currency":"1","amount":"5976","avatar":null,"avatar_base64":null,"amount_format":"5,976"},{"race":"2018-03-26","rank":"25","uid":"0","account":"Allexielxie","game":"2","currency":"1","amount":"5806","avatar":null,"avatar_base64":null,"amount_format":"5,806"},{"race":"2018-03-26","rank":"26","uid":"0","account":"Aelurora","game":"2","currency":"1","amount":"5709","avatar":null,"avatar_base64":null,"amount_format":"5,709"},{"race":"2018-03-26","rank":"27","uid":"0","account":"smileysmoon","game":"2","currency":"1","amount":"5654","avatar":null,"avatar_base64":null,"amount_format":"5,654"},{"race":"2018-03-26","rank":"28","uid":"0","account":"DuDuCiaBR","game":"2","currency":"1","amount":"5610","avatar":null,"avatar_base64":null,"amount_format":"5,610"},{"race":"2018-03-26","rank":"29","uid":"0","account":"thanatanthrope","game":"2","currency":"1","amount":"5507","avatar":null,"avatar_base64":null,"amount_format":"5,507"},{"race":"2018-03-26","rank":"30","uid":"0","account":"Mechanisms","game":"2","currency":"1","amount":"5401","avatar":null,"avatar_base64":null,"amount_format":"5,401"},{"race":"2018-03-26","rank":"31","uid":"0","account":"Solution85","game":"2","currency":"1","amount":"5360","avatar":null,"avatar_base64":null,"amount_format":"5,360"},{"race":"2018-03-26","rank":"32","uid":"0","account":"MinMinLight","game":"2","currency":"1","amount":"5205","avatar":null,"avatar_base64":null,"amount_format":"5,205"},{"race":"2018-03-26","rank":"33","uid":"0","account":"TheuberClips","game":"2","currency":"1","amount":"5156","avatar":null,"avatar_base64":null,"amount_format":"5,156"},{"race":"2018-03-26","rank":"34","uid":"0","account":"DonaldFDN","game":"2","currency":"1","amount":"5107","avatar":null,"avatar_base64":null,"amount_format":"5,107"},{"race":"2018-03-26","rank":"35","uid":"0","account":"starwind13","game":"2","currency":"1","amount":"4923","avatar":null,"avatar_base64":null,"amount_format":"4,923"},{"race":"2018-03-26","rank":"36","uid":"0","account":"sirtrollingmid","game":"2","currency":"1","amount":"4783","avatar":null,"avatar_base64":null,"amount_format":"4,783"},{"race":"2018-03-26","rank":"37","uid":"0","account":"Lamanosoff","game":"2","currency":"1","amount":"4771","avatar":null,"avatar_base64":null,"amount_format":"4,771"},{"race":"2018-03-26","rank":"38","uid":"0","account":"fireballz","game":"2","currency":"1","amount":"4708","avatar":null,"avatar_base64":null,"amount_format":"4,708"},{"race":"2018-03-26","rank":"39","uid":"0","account":"IVIrPorter","game":"2","currency":"1","amount":"4489","avatar":null,"avatar_base64":null,"amount_format":"4,489"},{"race":"2018-03-26","rank":"40","uid":"0","account":"shooster88","game":"2","currency":"1","amount":"4400","avatar":null,"avatar_base64":null,"amount_format":"4,400"},{"race":"2018-03-26","rank":"41","uid":"0","account":"AkuNoDjo","game":"2","currency":"1","amount":"4369","avatar":null,"avatar_base64":null,"amount_format":"4,369"},{"race":"2018-03-26","rank":"42","uid":"0","account":"MillerAP","game":"2","currency":"1","amount":"4306","avatar":null,"avatar_base64":null,"amount_format":"4,306"},{"race":"2018-03-26","rank":"43","uid":"0","account":"ultraZel","game":"2","currency":"1","amount":"4227","avatar":null,"avatar_base64":null,"amount_format":"4,227"},{"race":"2018-03-26","rank":"44","uid":"0","account":"NyanBrodeh","game":"2","currency":"1","amount":"4160","avatar":null,"avatar_base64":null,"amount_format":"4,160"},{"race":"2018-03-26","rank":"45","uid":"0","account":"AmuroRanger","game":"2","currency":"1","amount":"4099","avatar":null,"avatar_base64":null,"amount_format":"4,099"},{"race":"2018-03-26","rank":"46","uid":"0","account":"Tyranastrasz","game":"2","currency":"1","amount":"4076","avatar":null,"avatar_base64":null,"amount_format":"4,076"},{"race":"2018-03-26","rank":"47","uid":"0","account":"dkchinvt4u","game":"2","currency":"1","amount":"3998","avatar":null,"avatar_base64":null,"amount_format":"3,998"},{"race":"2018-03-26","rank":"48","uid":"0","account":"goalcurry","game":"2","currency":"1","amount":"3893","avatar":null,"avatar_base64":null,"amount_format":"3,893"},{"race":"2018-03-26","rank":"49","uid":"0","account":"Jeckel86","game":"2","currency":"1","amount":"3869","avatar":null,"avatar_base64":null,"amount_format":"3,869"},{"race":"2018-03-26","rank":"50","uid":"0","account":"ccw1212ccw","game":"2","currency":"1","amount":"3850","avatar":null,"avatar_base64":null,"amount_format":"3,850"},{"race":"2018-03-26","rank":"51","uid":"0","account":"bersi23132","game":"2","currency":"1","amount":"3768","avatar":null,"avatar_base64":null,"amount_format":"3,768"},{"race":"2018-03-26","rank":"52","uid":"0","account":"JeckelSplodes","game":"2","currency":"1","amount":"3767","avatar":null,"avatar_base64":null,"amount_format":"3,767"},{"race":"2018-03-26","rank":"53","uid":"0","account":"Zealotttommy","game":"2","currency":"1","amount":"3765","avatar":null,"avatar_base64":null,"amount_format":"3,765"},{"race":"2018-03-26","rank":"54","uid":"0","account":"danisonxtc","game":"2","currency":"1","amount":"3695","avatar":null,"avatar_base64":null,"amount_format":"3,695"},{"race":"2018-03-26","rank":"55","uid":"0","account":"MrDxxxxxom","game":"2","currency":"1","amount":"3623","avatar":null,"avatar_base64":null,"amount_format":"3,623"},{"race":"2018-03-26","rank":"56","uid":"0","account":"ForcedU2","game":"2","currency":"1","amount":"3582","avatar":null,"avatar_base64":null,"amount_format":"3,582"},{"race":"2018-03-26","rank":"57","uid":"0","account":"Cookiedous","game":"2","currency":"1","amount":"3580","avatar":null,"avatar_base64":null,"amount_format":"3,580"},{"race":"2018-03-26","rank":"58","uid":"0","account":"taewolfkk","game":"2","currency":"1","amount":"3575","avatar":null,"avatar_base64":null,"amount_format":"3,575"},{"race":"2018-03-26","rank":"59","uid":"0","account":"toiletsnake","game":"2","currency":"1","amount":"3562","avatar":null,"avatar_base64":null,"amount_format":"3,562"},{"race":"2018-03-26","rank":"60","uid":"0","account":"Tripleyou","game":"2","currency":"1","amount":"3532","avatar":null,"avatar_base64":null,"amount_format":"3,532"},{"race":"2018-03-26","rank":"61","uid":"0","account":"vittovi369","game":"2","currency":"1","amount":"3511","avatar":null,"avatar_base64":null,"amount_format":"3,511"},{"race":"2018-03-26","rank":"62","uid":"0","account":"aquiles20","game":"2","currency":"1","amount":"3487","avatar":null,"avatar_base64":null,"amount_format":"3,487"},{"race":"2018-03-26","rank":"63","uid":"0","account":"wesleygjr","game":"2","currency":"1","amount":"3400","avatar":null,"avatar_base64":null,"amount_format":"3,400"},{"race":"2018-03-26","rank":"64","uid":"0","account":"Kheldar75","game":"2","currency":"1","amount":"3379","avatar":null,"avatar_base64":null,"amount_format":"3,379"},{"race":"2018-03-26","rank":"65","uid":"0","account":"qqunouno","game":"2","currency":"1","amount":"3185","avatar":null,"avatar_base64":null,"amount_format":"3,185"},{"race":"2018-03-26","rank":"66","uid":"0","account":"xardas22das","game":"2","currency":"1","amount":"3126","avatar":null,"avatar_base64":null,"amount_format":"3,126"},{"race":"2018-03-26","rank":"67","uid":"0","account":"Vixlololol","game":"2","currency":"1","amount":"3016","avatar":null,"avatar_base64":null,"amount_format":"3,016"},{"race":"2018-03-26","rank":"68","uid":"0","account":"Kynosnos","game":"2","currency":"1","amount":"2846","avatar":null,"avatar_base64":null,"amount_format":"2,846"},{"race":"2018-03-26","rank":"69","uid":"0","account":"Entropic_Fire","game":"2","currency":"1","amount":"2757","avatar":null,"avatar_base64":null,"amount_format":"2,757"},{"race":"2018-03-26","rank":"70","uid":"0","account":"MasOyama","game":"2","currency":"1","amount":"2750","avatar":null,"avatar_base64":null,"amount_format":"2,750"},{"race":"2018-03-26","rank":"71","uid":"0","account":"Labudator","game":"2","currency":"1","amount":"2713","avatar":null,"avatar_base64":null,"amount_format":"2,713"},{"race":"2018-03-26","rank":"72","uid":"0","account":"Rinkeilxx","game":"2","currency":"1","amount":"2622","avatar":null,"avatar_base64":null,"amount_format":"2,622"},{"race":"2018-03-26","rank":"73","uid":"0","account":"robertune","game":"2","currency":"1","amount":"2579","avatar":null,"avatar_base64":null,"amount_format":"2,579"},{"race":"2018-03-26","rank":"74","uid":"0","account":"HejzHejz","game":"2","currency":"1","amount":"2573","avatar":null,"avatar_base64":null,"amount_format":"2,573"},{"race":"2018-03-26","rank":"75","uid":"0","account":"Rinkeilmox","game":"2","currency":"1","amount":"2489","avatar":null,"avatar_base64":null,"amount_format":"2,489"},{"race":"2018-03-26","rank":"76","uid":"0","account":"UberPeasant","game":"2","currency":"1","amount":"2482","avatar":null,"avatar_base64":null,"amount_format":"2,482"},{"race":"2018-03-26","rank":"77","uid":"0","account":"Pulpfiction","game":"2","currency":"1","amount":"2460","avatar":null,"avatar_base64":null,"amount_format":"2,460"},{"race":"2018-03-26","rank":"78","uid":"0","account":"siMoKMoK","game":"2","currency":"1","amount":"2404","avatar":null,"avatar_base64":null,"amount_format":"2,404"},{"race":"2018-03-26","rank":"79","uid":"0","account":"VitaminX","game":"2","currency":"1","amount":"2337","avatar":null,"avatar_base64":null,"amount_format":"2,337"},{"race":"2018-03-26","rank":"80","uid":"0","account":"hookeyisgreat","game":"2","currency":"1","amount":"2313","avatar":null,"avatar_base64":null,"amount_format":"2,313"},{"race":"2018-03-26","rank":"81","uid":"0","account":"rami1337","game":"2","currency":"1","amount":"2244","avatar":null,"avatar_base64":null,"amount_format":"2,244"},{"race":"2018-03-26","rank":"82","uid":"0","account":"Ireneuszz","game":"2","currency":"1","amount":"2200","avatar":null,"avatar_base64":null,"amount_format":"2,200"},{"race":"2018-03-26","rank":"83","uid":"0","account":"buhdunkadunk","game":"2","currency":"1","amount":"2189","avatar":null,"avatar_base64":null,"amount_format":"2,189"},{"race":"2018-03-26","rank":"84","uid":"0","account":"uTunTooM","game":"2","currency":"1","amount":"2165","avatar":null,"avatar_base64":null,"amount_format":"2,165"},{"race":"2018-03-26","rank":"85","uid":"0","account":"Arliusmoney","game":"2","currency":"1","amount":"2089","avatar":null,"avatar_base64":null,"amount_format":"2,089"},{"race":"2018-03-26","rank":"86","uid":"0","account":"PydosPydos","game":"2","currency":"1","amount":"2059","avatar":null,"avatar_base64":null,"amount_format":"2,059"},{"race":"2018-03-26","rank":"87","uid":"0","account":"Ancestrum","game":"2","currency":"1","amount":"2037","avatar":null,"avatar_base64":null,"amount_format":"2,037"},{"race":"2018-03-26","rank":"88","uid":"0","account":"Troumyuna","game":"2","currency":"1","amount":"2000","avatar":null,"avatar_base64":null,"amount_format":"2,000"},{"race":"2018-03-26","rank":"89","uid":"0","account":"malikerma","game":"2","currency":"1","amount":"1979","avatar":null,"avatar_base64":null,"amount_format":"1,979"},{"race":"2018-03-26","rank":"90","uid":"0","account":"Jeebiebie","game":"2","currency":"1","amount":"1918","avatar":null,"avatar_base64":null,"amount_format":"1,918"},{"race":"2018-03-26","rank":"91","uid":"0","account":"rtyurtyuu","game":"2","currency":"1","amount":"1876","avatar":null,"avatar_base64":null,"amount_format":"1,876"},{"race":"2018-03-26","rank":"92","uid":"0","account":"Ernne113","game":"2","currency":"1","amount":"1855","avatar":null,"avatar_base64":null,"amount_format":"1,855"},{"race":"2018-03-26","rank":"93","uid":"0","account":"DannyChu","game":"2","currency":"1","amount":"1753","avatar":null,"avatar_base64":null,"amount_format":"1,753"},{"race":"2018-03-26","rank":"93","uid":"0","account":"Hajiangchen","game":"2","currency":"1","amount":"1753","avatar":null,"avatar_base64":null,"amount_format":"1,753"},{"race":"2018-03-26","rank":"95","uid":"0","account":"megamarauder99","game":"2","currency":"1","amount":"1635","avatar":null,"avatar_base64":null,"amount_format":"1,635"},{"race":"2018-03-26","rank":"96","uid":"0","account":"QQQQQQQQ","game":"2","currency":"1","amount":"1634","avatar":null,"avatar_base64":null,"amount_format":"1,634"},{"race":"2018-03-26","rank":"97","uid":"0","account":"Blazedhaze","game":"2","currency":"1","amount":"1616","avatar":null,"avatar_base64":null,"amount_format":"1,616"},{"race":"2018-03-26","rank":"98","uid":"0","account":"YunSunnzy","game":"2","currency":"1","amount":"1337","avatar":null,"avatar_base64":null,"amount_format":"1,337"},{"race":"2018-03-26","rank":"99","uid":"0","account":"PUBGASIA","game":"2","currency":"1","amount":"1300","avatar":null,"avatar_base64":null,"amount_format":"1,300"},{"race":"2018-03-26","rank":"100","uid":"0","account":"Lamanosoff","game":"2","currency":"1","amount":"1244","avatar":null,"avatar_base64":null,"amount_format":"1,244"},{"race":"2018-03-26","rank":"101","uid":"0","account":"Logicals","game":"2","currency":"1","amount":"1205","avatar":null,"avatar_base64":null,"amount_format":"1,205"},{"race":"2018-03-26","rank":"102","uid":"0","account":"OplOplIU","game":"2","currency":"1","amount":"1169","avatar":null,"avatar_base64":null,"amount_format":"1,169"},{"race":"2018-03-26","rank":"103","uid":"0","account":"LeeFyuiNtt","game":"2","currency":"1","amount":"1160","avatar":null,"avatar_base64":null,"amount_format":"1,160"},{"race":"2018-03-26","rank":"104","uid":"0","account":"NoooQoPPoQ","game":"2","currency":"1","amount":"1153","avatar":null,"avatar_base64":null,"amount_format":"1,153"},{"race":"2018-03-26","rank":"105","uid":"0","account":"luxxxuoi","game":"2","currency":"1","amount":"1138","avatar":null,"avatar_base64":null,"amount_format":"1,138"},{"race":"2018-03-26","rank":"106","uid":"0","account":"YooNooAcc","game":"2","currency":"1","amount":"1089","avatar":null,"avatar_base64":null,"amount_format":"1,089"},{"race":"2018-03-26","rank":"107","uid":"0","account":"Taeyeon309","game":"2","currency":"1","amount":"1034","avatar":null,"avatar_base64":null,"amount_format":"1,034"},{"race":"2018-03-26","rank":"108","uid":"0","account":"Antosianer","game":"2","currency":"1","amount":"999","avatar":null,"avatar_base64":null,"amount_format":"999"},{"race":"2018-03-26","rank":"109","uid":"0","account":"Sniperror","game":"2","currency":"1","amount":"986","avatar":null,"avatar_base64":null,"amount_format":"986"},{"race":"2018-03-26","rank":"110","uid":"0","account":"moDBaseTk","game":"2","currency":"1","amount":"931","avatar":null,"avatar_base64":null,"amount_format":"931"},{"race":"2018-03-26","rank":"111","uid":"0","account":"KruxKhan","game":"2","currency":"1","amount":"925","avatar":null,"avatar_base64":null,"amount_format":"925"},{"race":"2018-03-26","rank":"112","uid":"0","account":"Teemooooo","game":"2","currency":"1","amount":"922","avatar":null,"avatar_base64":null,"amount_format":"922"},{"race":"2018-03-26","rank":"113","uid":"0","account":"Pannicus","game":"2","currency":"1","amount":"895","avatar":null,"avatar_base64":null,"amount_format":"895"},{"race":"2018-03-26","rank":"114","uid":"0","account":"MoneyMoon","game":"2","currency":"1","amount":"813","avatar":null,"avatar_base64":null,"amount_format":"813"},{"race":"2018-03-26","rank":"115","uid":"0","account":"Nephalim","game":"2","currency":"1","amount":"735","avatar":null,"avatar_base64":null,"amount_format":"735"},{"race":"2018-03-26","rank":"116","uid":"0","account":"CFqueeN","game":"2","currency":"1","amount":"707","avatar":null,"avatar_base64":null,"amount_format":"707"},{"race":"2018-03-26","rank":"117","uid":"0","account":"Immijiee","game":"2","currency":"1","amount":"702","avatar":null,"avatar_base64":null,"amount_format":"702"},{"race":"2018-03-26","rank":"118","uid":"0","account":"Dunnompet","game":"2","currency":"1","amount":"606","avatar":null,"avatar_base64":null,"amount_format":"606"},{"race":"2018-03-26","rank":"119","uid":"0","account":"nihaohaoa","game":"2","currency":"1","amount":"499","avatar":null,"avatar_base64":null,"amount_format":"499"},{"race":"2018-03-26","rank":"120","uid":"0","account":"CAM11111111","game":"2","currency":"1","amount":"469","avatar":null,"avatar_base64":null,"amount_format":"469"},{"race":"2018-03-26","rank":"121","uid":"0","account":"tianxingjian","game":"2","currency":"1","amount":"443","avatar":null,"avatar_base64":null,"amount_format":"443"},{"race":"2018-03-26","rank":"122","uid":"0","account":"wocaonimei","game":"2","currency":"1","amount":"407","avatar":null,"avatar_base64":null,"amount_format":"407"},{"race":"2018-03-26","rank":"123","uid":"0","account":"alexlover","game":"2","currency":"1","amount":"355","avatar":null,"avatar_base64":null,"amount_format":"355"},{"race":"2018-03-26","rank":"124","uid":"0","account":"TOTQAumzz","game":"2","currency":"1","amount":"340","avatar":null,"avatar_base64":null,"amount_format":"340"},{"race":"2018-03-26","rank":"125","uid":"0","account":"xiangIDxiang","game":"2","currency":"1","amount":"318","avatar":null,"avatar_base64":null,"amount_format":"318"},{"race":"2018-03-26","rank":"126","uid":"0","account":"TaeTaerrg","game":"2","currency":"1","amount":"313","avatar":null,"avatar_base64":null,"amount_format":"313"},{"race":"2018-03-26","rank":"127","uid":"0","account":"dazhongwen","game":"2","currency":"1","amount":"216","avatar":null,"avatar_base64":null,"amount_format":"216"},{"race":"2018-03-26","rank":"128","uid":"0","account":"dundundunn","game":"2","currency":"1","amount":"211","avatar":null,"avatar_base64":null,"amount_format":"211"},{"race":"2018-03-26","rank":"129","uid":"0","account":"rangerland","game":"2","currency":"1","amount":"195","avatar":null,"avatar_base64":null,"amount_format":"195"},{"race":"2018-03-26","rank":"129","uid":"0","account":"nuyaowen","game":"2","currency":"1","amount":"195","avatar":null,"avatar_base64":null,"amount_format":"195"},{"race":"2018-03-26","rank":"131","uid":"0","account":"zhuananguan","game":"2","currency":"1","amount":"182","avatar":null,"avatar_base64":null,"amount_format":"182"},{"race":"2018-03-26","rank":"132","uid":"0","account":"xiao1xiao1","game":"2","currency":"1","amount":"180","avatar":null,"avatar_base64":null,"amount_format":"180"},{"race":"2018-03-26","rank":"133","uid":"0","account":"Nicotianxin","game":"2","currency":"1","amount":"159","avatar":null,"avatar_base64":null,"amount_format":"159"},{"race":"2018-03-26","rank":"134","uid":"0","account":"kudashishi","game":"2","currency":"1","amount":"157","avatar":null,"avatar_base64":null,"amount_format":"157"},{"race":"2018-03-26","rank":"135","uid":"0","account":"balawanxie","game":"2","currency":"1","amount":"149","avatar":null,"avatar_base64":null,"amount_format":"149"},{"race":"2018-03-26","rank":"135","uid":"0","account":"nishuoaiwo","game":"2","currency":"1","amount":"149","avatar":null,"avatar_base64":null,"amount_format":"149"},{"race":"2018-03-26","rank":"137","uid":"0","account":"mingmingo","game":"2","currency":"1","amount":"142","avatar":null,"avatar_base64":null,"amount_format":"142"},{"race":"2018-03-26","rank":"138","uid":"0","account":"Jessicurry","game":"2","currency":"1","amount":"136","avatar":null,"avatar_base64":null,"amount_format":"136"},{"race":"2018-03-26","rank":"139","uid":"0","account":"Wendidiary","game":"2","currency":"1","amount":"133","avatar":null,"avatar_base64":null,"amount_format":"133"},{"race":"2018-03-26","rank":"140","uid":"0","account":"hanguomei","game":"2","currency":"1","amount":"131","avatar":null,"avatar_base64":null,"amount_format":"131"},{"race":"2018-03-26","rank":"141","uid":"0","account":"gongyein","game":"2","currency":"1","amount":"114","avatar":null,"avatar_base64":null,"amount_format":"114"},{"race":"2018-03-26","rank":"142","uid":"0","account":"leaderboard","game":"2","currency":"1","amount":"112","avatar":null,"avatar_base64":null,"amount_format":"112"},{"race":"2018-03-26","rank":"143","uid":"0","account":"niyaowo","game":"2","currency":"1","amount":"111","avatar":null,"avatar_base64":null,"amount_format":"111"},{"race":"2018-03-26","rank":"144","uid":"0","account":"pluoiiowc","game":"2","currency":"1","amount":"105","avatar":null,"avatar_base64":null,"amount_format":"105"},{"race":"2018-03-26","rank":"145","uid":"0","account":"zhenzhunai","game":"2","currency":"1","amount":"103","avatar":null,"avatar_base64":null,"amount_format":"103"},{"race":"2018-03-26","rank":"146","uid":"0","account":"OcQcOcQcO","game":"2","currency":"1","amount":"96","avatar":null,"avatar_base64":null,"amount_format":"96"},{"race":"2018-03-26","rank":"147","uid":"0","account":"GSWmeizi","game":"2","currency":"1","amount":"93","avatar":null,"avatar_base64":null,"amount_format":"93"},{"race":"2018-03-26","rank":"148","uid":"0","account":"PUBGASIACN","game":"2","currency":"1","amount":"83","avatar":null,"avatar_base64":null,"amount_format":"83"},{"race":"2018-03-26","rank":"149","uid":"0","account":"kingcurry","game":"2","currency":"1","amount":"80","avatar":null,"avatar_base64":null,"amount_format":"80"},{"race":"2018-03-26","rank":"150","uid":"0","account":"buyaolie","game":"2","currency":"1","amount":"69","avatar":null,"avatar_base64":null,"amount_format":"69"},{"race":"2018-03-26","rank":"151","uid":"0","account":"Kingjames","game":"2","currency":"1","amount":"67","avatar":null,"avatar_base64":null,"amount_format":"67"},{"race":"2018-03-26","rank":"152","uid":"0","account":"Gremmmmm","game":"2","currency":"1","amount":"66","avatar":null,"avatar_base64":null,"amount_format":"66"},{"race":"2018-03-26","rank":"153","uid":"0","account":"shanghaiCU","game":"2","currency":"1","amount":"47","avatar":null,"avatar_base64":null,"amount_format":"47"},{"race":"2018-03-26","rank":"154","uid":"0","account":"woxshuang","game":"2","currency":"1","amount":"46","avatar":null,"avatar_base64":null,"amount_format":"46"},{"race":"2018-03-26","rank":"155","uid":"0","account":"Guommnic","game":"2","currency":"1","amount":"44","avatar":null,"avatar_base64":null,"amount_format":"44"},{"race":"2018-03-26","rank":"156","uid":"0","account":"destiny222","game":"2","currency":"1","amount":"43","avatar":null,"avatar_base64":null,"amount_format":"43"},{"race":"2018-03-26","rank":"157","uid":"0","account":"nihuipapa","game":"2","currency":"1","amount":"41","avatar":null,"avatar_base64":null,"amount_format":"41"},{"race":"2018-03-26","rank":"158","uid":"0","account":"jianjian","game":"2","currency":"1","amount":"39","avatar":null,"avatar_base64":null,"amount_format":"39"},{"race":"2018-03-26","rank":"159","uid":"0","account":"yoooooooona","game":"2","currency":"1","amount":"38","avatar":null,"avatar_base64":null,"amount_format":"38"},{"race":"2018-03-26","rank":"160","uid":"0","account":"shuziren853","game":"2","currency":"1","amount":"36","avatar":null,"avatar_base64":null,"amount_format":"36"},{"race":"2018-03-26","rank":"161","uid":"0","account":"DiDiyuewan","game":"2","currency":"1","amount":"35","avatar":null,"avatar_base64":null,"amount_format":"35"},{"race":"2018-03-26","rank":"161","uid":"0","account":"newbbiew","game":"2","currency":"1","amount":"35","avatar":null,"avatar_base64":null,"amount_format":"35"},{"race":"2018-03-26","rank":"163","uid":"0","account":"zhidaotaiduo","game":"2","currency":"1","amount":"34","avatar":null,"avatar_base64":null,"amount_format":"34"},{"race":"2018-03-26","rank":"164","uid":"0","account":"gunnimeimei","game":"2","currency":"1","amount":"21","avatar":null,"avatar_base64":null,"amount_format":"21"},{"race":"2018-03-26","rank":"165","uid":"0","account":"ribenmei","game":"2","currency":"1","amount":"19","avatar":null,"avatar_base64":null,"amount_format":"19"},{"race":"2018-03-26","rank":"166","uid":"0","account":"FQUeenNNd","game":"2","currency":"1","amount":"14","avatar":null,"avatar_base64":null,"amount_format":"14"},{"race":"2018-03-26","rank":"167","uid":"0","account":"sunsudkid","game":"2","currency":"1","amount":"4","avatar":null,"avatar_base64":null,"amount_format":"4"},{"race":"2018-03-26","rank":"168","uid":"0","account":"Iuwodecai","game":"2","currency":"1","amount":"2","avatar":null,"avatar_base64":null,"amount_format":"2"}],"user_rank":null,"uid":0,"username":"","date":{"start_date":"2018-03-26","end_date":"2018-04-01"}}}
